setup.cfg
setup.py
postageapp/__init__.py
postageapp/config.py
postageapp/request.py
postageapp.egg-info/PKG-INFO
postageapp.egg-info/SOURCES.txt
postageapp.egg-info/dependency_links.txt
postageapp.egg-info/not-zip-safe
postageapp.egg-info/requires.txt
postageapp.egg-info/top_level.txt