Metadata-Version: 1.0
Name: postageapp
Version: 0.1.1
Summary: Library for sending email via the PostageApp service
Home-page: http://github.com/postageapp/postageapp-python
Author: Scott Tadman
Author-email: tadman@postageapp.com
License: MIT
Platform: UNKNOWN
